log_time_to_tempo/__init__.py
log_time_to_tempo/_jira.py
log_time_to_tempo/_logging.py
log_time_to_tempo/_time.py
log_time_to_tempo/caching.py
log_time_to_tempo/tempo.py
log_time_to_tempo/cli/__init__.py
log_time_to_tempo/cli/_sparkline.py
log_time_to_tempo/cli/alias.py
log_time_to_tempo/cli/completions.py
log_time_to_tempo/cli/config.py
log_time_to_tempo/cli/main.py
log_time_to_tempo-0.0.9.dist-info/METADATA
log_time_to_tempo-0.0.9.dist-info/WHEEL
log_time_to_tempo-0.0.9.dist-info/entry_points.txt
log_time_to_tempo-0.0.9.dist-info/licenses/LICENSE
log_time_to_tempo-0.0.9.dist-info/RECORD
