Metadata-Version: 2.4
Name: log-time-to-tempo
Version: 0.0.9
Summary: Log your work time to tempo from the command line.
Project-URL: Documentation, https://github.com/jannismain/log-time-to-tempo#readme
Project-URL: Issues, https://github.com/jannismain/log-time-to-tempo/issues
Project-URL: Source, https://github.com/jannismain/log-time-to-tempo
Author-email: Jannis Mainczyk <jannis.mainczyk@codecentric.de>
License-File: LICENSE
Keywords: cli,jira,tempo
Classifier: Development Status :: 4 - Beta
Classifier: Programming Language :: Python
Classifier: Programming Language :: Python :: 3.8
Classifier: Programming Language :: Python :: 3.9
Classifier: Programming Language :: Python :: 3.10
Classifier: Programming Language :: Python :: 3.11
Classifier: Programming Language :: Python :: 3.12
Classifier: Programming Language :: Python :: Implementation :: CPython
Classifier: Programming Language :: Python :: Implementation :: PyPy
Requires-Python: >=3.11
Requires-Dist: click>=8.2
Requires-Dist: coloredlogs
Requires-Dist: dateparser
Requires-Dist: jira
Requires-Dist: keyring
Requires-Dist: keyrings-alt
Requires-Dist: pydantic
Requires-Dist: python-dateutil
Requires-Dist: python-dotenv
Requires-Dist: requests
Requires-Dist: rich
Requires-Dist: simple-term-menu
Requires-Dist: sparklines
Requires-Dist: typer
